analogio.py
bitbangio.py
board.py
busio.py
digitalio.py
keypad.py
micropython.py
neopixel_write.py
onewireio.py
pulseio.py
pwmio.py
rainbowio.py
usb_hid.py
adafruit_blinka/__init__.py
adafruit_blinka/agnostic/__init__.py
adafruit_blinka/agnostic/time.py
adafruit_blinka/board/OLIMEX_LIME2.py
adafruit_blinka/board/__init__.py
adafruit_blinka/board/binho_nova.py
adafruit_blinka/board/clockworkcpi3.py
adafruit_blinka/board/coral_dev_board.py
adafruit_blinka/board/coral_dev_board_mini.py
adafruit_blinka/board/dragonboard_410c.py
adafruit_blinka/board/feather_can_u2if.py
adafruit_blinka/board/feather_epd_u2if.py
adafruit_blinka/board/feather_huzzah.py
adafruit_blinka/board/feather_rfm_u2if.py
adafruit_blinka/board/feather_u2if.py
adafruit_blinka/board/ftdi_ft2232h.py
adafruit_blinka/board/ftdi_ft232h.py
adafruit_blinka/board/ftdi_ft4232h.py
adafruit_blinka/board/generic_agnostic_board.py
adafruit_blinka/board/generic_linux_pc.py
adafruit_blinka/board/giantboard.py
adafruit_blinka/board/greatfet_one.py
adafruit_blinka/board/hifive_unleashed.py
adafruit_blinka/board/itsybitsy_u2if.py
adafruit_blinka/board/kb2040_u2if.py
adafruit_blinka/board/lichee_rv.py
adafruit_blinka/board/licheepi_4a.py
adafruit_blinka/board/macropad_u2if.py
adafruit_blinka/board/microchip_mcp2221.py
adafruit_blinka/board/milkv_duo.py
adafruit_blinka/board/nodemcu.py
adafruit_blinka/board/pico_u2if.py
adafruit_blinka/board/pineH64.py
adafruit_blinka/board/pyboard.py
adafruit_blinka/board/qt2040_trinkey_u2if.py
adafruit_blinka/board/qtpy_u2if.py
adafruit_blinka/board/radxa_x4_u2if.py
adafruit_blinka/board/rp2040_one_u2if.py
adafruit_blinka/board/soPine.py
adafruit_blinka/board/tritium-h3.py
adafruit_blinka/board/udoo_x86ultra.py
adafruit_blinka/board/vivid_unit.py
adafruit_blinka/board/x86j41x5.py
adafruit_blinka/board/ameridroid/__init__.py
adafruit_blinka/board/ameridroid/indiedroid_nova.py
adafruit_blinka/board/bananapi/__init__.py
adafruit_blinka/board/bananapi/bpiai2h.py
adafruit_blinka-8.66.1.dist-info/licenses/LICENSE
adafruit_blinka-8.66.1.dist-info/METADATA
adafruit_blinka-8.66.1.dist-info/WHEEL
adafruit_blinka-8.66.1.dist-info/top_level.txt
adafruit_blinka-8.66.1.dist-info/RECORD
