Metadata-Version: 2.4
Name: Adafruit-Blinka
Version: 8.66.1
Summary: CircuitPython APIs for non-CircuitPython versions of Python such as CPython on Linux and MicroPython.
Home-page: https://github.com/adafruit/Adafruit_Blinka
Author: Adafruit Industries
Author-email: circuitpython@adafruit.com
License: MIT
Classifier: License :: OSI Approved :: MIT License
Classifier: Programming Language :: Python
Classifier: Programming Language :: Python :: 3
Classifier: Programming Language :: Python :: 3.7
Classifier: Programming Language :: Python :: Implementation :: MicroPython
Requires-Python: >=3.7.0
License-File: LICENSE
Requires-Dist: Adafruit-PlatformDetect>=3.70.1
Requires-Dist: Adafruit-PureIO>=1.1.7
Requires-Dist: binho-host-adapter>=0.1.6
Requires-Dist: pyftdi>=0.40.0
Requires-Dist: adafruit-circuitpython-typing
Requires-Dist: sysv_ipc>=1.1.0; sys_platform == "linux" and platform_machine != "mips"
Requires-Dist: toml>=0.10.2; python_version < "3.11"
Dynamic: author
Dynamic: author-email
Dynamic: classifier
Dynamic: description
Dynamic: description-content-type
Dynamic: home-page
Dynamic: license
Dynamic: license-file
Dynamic: requires-dist
Dynamic: requires-python
Dynamic: summary
